iteratedc/__init__.py
iteratedc/iterators.py
iteratedc/tree.py
iteratedc/visitor.py
iteratedc-0.6.5.dist-info/LICENSE
iteratedc-0.6.5.dist-info/METADATA
iteratedc-0.6.5.dist-info/WHEEL
iteratedc-0.6.5.dist-info/top_level.txt
iteratedc-0.6.5.dist-info/RECORD
