Metadata-Version: 2.1
Name: iteratedc
Version: 0.6.5
Summary: Iterator for data classes
Home-page: https://github.com/carstencodes/iteratedc
Author: Carsten Igel
Author-email: cig@bite-that-bit.de
License: BSD 3-Clause
Platform: UNKNOWN
Classifier: Development Status :: 4 - Beta
Classifier: Intended Audience :: Developers
Classifier: Operating System :: OS Independent
Classifier: Programming Language :: Python :: 3.8
Classifier: Programming Language :: Python :: 3.9
Classifier: Topic :: Software Development :: Libraries :: Python Modules
Classifier: Topic :: System
Classifier: Typing :: Typed
Requires-Python: >=3.8, < 4
